setup.py
pysimpleinjector.egg-info/PKG-INFO
pysimpleinjector.egg-info/SOURCES.txt
pysimpleinjector.egg-info/dependency_links.txt
pysimpleinjector.egg-info/top_level.txt
simpleinjector/__init__.py