Metadata-Version: 1.0
Name: pysimpleinjector
Version: 1.1
Summary: An extremely simple framework-independent dependency injector.
Home-page: https://github.com/hobarrera/simpleinjector
Author: Hugo Osvaldo Barrera
Author-email: hugo@barrera.io
License: ISC
Platform: UNKNOWN
